glovo_community_utils_data_quality_generator/__init__.py
glovo_community_utils_data_quality_generator-0.0.0.dist-info/METADATA
glovo_community_utils_data_quality_generator-0.0.0.dist-info/WHEEL
glovo_community_utils_data_quality_generator-0.0.0.dist-info/top_level.txt
glovo_community_utils_data_quality_generator-0.0.0.dist-info/RECORD
